{
    "10102": {
        "name": "Vangertz Shield",
        "stock": "31",
        "volume": "826628",
        "price": "18000"
    },
    "10103": {
        "name": "Axion Shield",
        "stock": "219",
        "volume": "1252093",
        "price": "21100"
    },
    "10105": {
        "name": "Kite Shield",
        "stock": "251",
        "volume": "502720",
        "price": "24200"
    },
    "10124": {
        "name": "Krea Shield",
        "stock": "151",
        "volume": "1228456",
        "price": "27200"
    },
    "10125": {
        "name": "Rosar Shield",
        "stock": "1952",
        "volume": "872574",
        "price": "55500"
    },
    "10138": {
        "name": "Nouver Shield",
        "stock": "29",
        "volume": "34318",
        "price": "167000000"
    },
    "10140": {
        "name": "Kutum Shield",
        "stock": "55",
        "volume": "61759",
        "price": "180000000"
    },
    "10303": {
        "name": "Bronze Dagger",
        "stock": "18",
        "volume": "1495939",
        "price": "18000"
    },
    "10304": {
        "name": "Steel Dagger",
        "stock": "137",
        "volume": "2496061",
        "price": "21100"
    },
    "10305": {
        "name": "Parrying Dagger",
        "stock": "424",
        "volume": "640817",
        "price": "24200"
    },
    "10324": {
        "name": "Krea Dagger",
        "stock": "23",
        "volume": "651659",
        "price": "27200"
    },
    "10325": {
        "name": "Rosar Dagger",
        "stock": "23",
        "volume": "633793",
        "price": "55500"
    },
    "10338": {
        "name": "Nouver Dagger",
        "stock": "28",
        "volume": "44832",
        "price": "167000000"
    },
    "10340": {
        "name": "Kutum Dagger",
        "stock": "43",
        "volume": "56144",
        "price": "180000000"
    },
    "10503": {
        "name": "Helrick Talisman",
        "stock": "14",
        "volume": "499511",
        "price": "18000"
    },
    "10504": {
        "name": "Jubre Talisman",
        "stock": "123",
        "volume": "676374",
        "price": "21100"
    },
    "10505": {
        "name": "Rhik Talisman",
        "stock": "19",
        "volume": "99915",
        "price": "24200"
    },
    "10524": {
        "name": "Krea Talisman",
        "stock": "65",
        "volume": "195883",
        "price": "27200"
    },
    "10525": {
        "name": "Rosar Talisman",
        "stock": "171",
        "volume": "1119629",
        "price": "55500"
    },
    "10538": {
        "name": "Nouver Talisman",
        "stock": "40",
        "volume": "21999",
        "price": "167000000"
    },
    "10540": {
        "name": "Kutum Talisman",
        "stock": "49",
        "volume": "31375",
        "price": "180000000"
    },
    "10703": {
        "name": "Saiyer Ornamental Knot",
        "stock": "89",
        "volume": "1030905",
        "price": "18000"
    },
    "10704": {
        "name": "Oros Ornamental Knot",
        "stock": "2693",
        "volume": "1496591",
        "price": "21100"
    },
    "10705": {
        "name": "Theos Ornamental Knot",
        "stock": "2559",
        "volume": "512980",
        "price": "24200"
    },
    "10724": {
        "name": "Krea Ornamental Knot",
        "stock": "117",
        "volume": "913406",
        "price": "27200"
    },
    "10725": {
        "name": "Rosar Ornamental Knot",
        "stock": "92",
        "volume": "197510",
        "price": "55500"
    },
    "10738": {
        "name": "Nouver Ornamental Knot",
        "stock": "28",
        "volume": "28313",
        "price": "167000000"
    },
    "10740": {
        "name": "Kutum Ornamental Knot",
        "stock": "23",
        "volume": "35267",
        "price": "180000000"
    },
    "11303": {
        "name": "Leather Vambrace",
        "stock": "6",
        "volume": "509850",
        "price": "18000"
    },
    "11304": {
        "name": "Scale Vambrace",
        "stock": "5483",
        "volume": "887916",
        "price": "21100"
    },
    "11305": {
        "name": "Iron Vambrace",
        "stock": "1545",
        "volume": "328733",
        "price": "24200"
    },
    "11324": {
        "name": "Krea Vambrace",
        "stock": "492",
        "volume": "910718",
        "price": "27200"
    },
    "11325": {
        "name": "Rosar Vambrace",
        "stock": "2431",
        "volume": "805942",
        "price": "55500"
    },
    "11338": {
        "name": "Nouver Vambrace",
        "stock": "45",
        "volume": "28700",
        "price": "167000000"
    },
    "11340": {
        "name": "Kutum Vambrace",
        "stock": "67",
        "volume": "43617",
        "price": "180000000"
    },
    "13003": {
        "name": "Incense Trinket",
        "stock": "27",
        "volume": "472618",
        "price": "18000"
    },
    "13004": {
        "name": "Needle Trinket",
        "stock": "459",
        "volume": "594133",
        "price": "21100"
    },
    "13005": {
        "name": "Blade Trinket",
        "stock": "269",
        "volume": "80193",
        "price": "24200"
    },
    "13024": {
        "name": "Krea Trinket",
        "stock": "931",
        "volume": "262246",
        "price": "27200"
    },
    "13025": {
        "name": "Rosar Trinket",
        "stock": "1233",
        "volume": "423047",
        "price": "55500"
    },
    "13038": {
        "name": "Nouver Trinket",
        "stock": "14",
        "volume": "7683",
        "price": "167000000"
    },
    "13040": {
        "name": "Kutum Trinket",
        "stock": "28",
        "volume": "11972",
        "price": "180000000"
    },
    "13103": {
        "name": "Black Warrior Horn Bow",
        "stock": "2",
        "volume": "952169",
        "price": "18000"
    },
    "13104": {
        "name": "White Horn Bow",
        "stock": "8",
        "volume": "897737",
        "price": "21100"
    },
    "13105": {
        "name": "White Warrior Horn Bow",
        "stock": "1",
        "volume": "447995",
        "price": "24200"
    },
    "13124": {
        "name": "Krea Horn Bow",
        "stock": "33",
        "volume": "409520",
        "price": "27200"
    },
    "13125": {
        "name": "Rosar Horn Bow",
        "stock": "19",
        "volume": "337360",
        "price": "55500"
    },
    "13138": {
        "name": "Nouver Horn Bow",
        "stock": "39",
        "volume": "23734",
        "price": "167000000"
    },
    "13140": {
        "name": "Kutum Horn Bow",
        "stock": "51",
        "volume": "35512",
        "price": "180000000"
    },
    "13503": {
        "name": "Ascending Noble Sword",
        "stock": "118",
        "volume": "279963",
        "price": "18000"
    },
    "13504": {
        "name": "Crow Noble Sword",
        "stock": "6127",
        "volume": "694709",
        "price": "21100"
    },
    "13505": {
        "name": "Mistress Noble Sword",
        "stock": "3563",
        "volume": "251542",
        "price": "24200"
    },
    "13524": {
        "name": "Krea Noble Sword",
        "stock": "3979",
        "volume": "397231",
        "price": "27200"
    },
    "13525": {
        "name": "Rosar Noble Sword",
        "stock": "73",
        "volume": "129078",
        "price": "55500"
    },
    "13538": {
        "name": "Nouver Noble Sword",
        "stock": "38",
        "volume": "17603",
        "price": "167000000"
    },
    "13540": {
        "name": "Kutum Noble Sword",
        "stock": "27",
        "volume": "29750",
        "price": "180000000"
    },
    "13803": {
        "name": "Bhatu Ra'ghon",
        "stock": "115",
        "volume": "145300",
        "price": "18000"
    },
    "13804": {
        "name": "Ganatte Ra'ghon",
        "stock": "6064",
        "volume": "437608",
        "price": "21100"
    },
    "13805": {
        "name": "Sharos Ra'ghon",
        "stock": "767",
        "volume": "51106",
        "price": "24200"
    },
    "13824": {
        "name": "Krea Ra'ghon",
        "stock": "3948",
        "volume": "501494",
        "price": "27200"
    },
    "13825": {
        "name": "Rosar Ra'ghon",
        "stock": "3505",
        "volume": "503284",
        "price": "55500"
    },
    "13838": {
        "name": "Nouver Ra'ghon",
        "stock": "25",
        "volume": "13962",
        "price": "167000000"
    },
    "13840": {
        "name": "Kutum Ra'ghon",
        "stock": "57",
        "volume": "20484",
        "price": "180000000"
    },
    "14503": {
        "name": "Quitar Kunai",
        "stock": "79",
        "volume": "968394",
        "price": "18000"
    },
    "14504": {
        "name": "Estique Kunai",
        "stock": "2652",
        "volume": "1078065",
        "price": "21100"
    },
    "14505": {
        "name": "Tadd Kunai",
        "stock": "1537",
        "volume": "426239",
        "price": "24200"
    },
    "14524": {
        "name": "Krea Kunai",
        "stock": "1759",
        "volume": "412161",
        "price": "27200"
    },
    "14525": {
        "name": "Rosar Kunai",
        "stock": "257",
        "volume": "158238",
        "price": "55500"
    },
    "14538": {
        "name": "Nouver Kunai",
        "stock": "23",
        "volume": "9151",
        "price": "167000000"
    },
    "14540": {
        "name": "Kutum Kunai",
        "stock": "29",
        "volume": "13193",
        "price": "180000000"
    },
    "14603": {
        "name": "Quitar Shuriken",
        "stock": "591",
        "volume": "974578",
        "price": "18000"
    },
    "14604": {
        "name": "Estique Shuriken",
        "stock": "4533",
        "volume": "1109628",
        "price": "21100"
    },
    "14605": {
        "name": "Tadd Shuriken",
        "stock": "1728",
        "volume": "425865",
        "price": "24200"
    },
    "14624": {
        "name": "Krea Shuriken",
        "stock": "2594",
        "volume": "406853",
        "price": "27200"
    },
    "14625": {
        "name": "Rosar Shuriken",
        "stock": "36",
        "volume": "158625",
        "price": "55500"
    },
    "14638": {
        "name": "Nouver Shuriken",
        "stock": "12",
        "volume": "15014",
        "price": "167000000"
    },
    "14640": {
        "name": "Kutum Shuriken",
        "stock": "34",
        "volume": "20374",
        "price": "180000000"
    },
    "692504": {
        "name": "Ahin Haladie",
        "stock": "10044",
        "volume": "292706",
        "price": "18000"
    },
    "692505": {
        "name": "Baduum Haladie",
        "stock": "7141",
        "volume": "146121",
        "price": "21100"
    },
    "692506": {
        "name": "Neshal Haladie",
        "stock": "7115",
        "volume": "75892",
        "price": "24200"
    },
    "692510": {
        "name": "Krea Haladie",
        "stock": "2067",
        "volume": "27073",
        "price": "27200"
    },
    "692511": {
        "name": "Rosar Haladie",
        "stock": "1719",
        "volume": "60126",
        "price": "55500"
    },
    "692514": {
        "name": "Nouver Haladie",
        "stock": "28",
        "volume": "6927",
        "price": "167000000"
    },
    "692516": {
        "name": "Kutum Haladie",
        "stock": "35",
        "volume": "7792",
        "price": "180000000"
    },
    "719003": {
        "name": "Saiyer Vitclari",
        "stock": "8442",
        "volume": "766400",
        "price": "18000"
    },
    "719004": {
        "name": "Oros Vitclari",
        "stock": "9072",
        "volume": "646451",
        "price": "21100"
    },
    "719005": {
        "name": "Theos Vitclari",
        "stock": "7650",
        "volume": "399643",
        "price": "24200"
    },
    "719024": {
        "name": "Krea Vitclari",
        "stock": "3414",
        "volume": "189644",
        "price": "27200"
    },
    "719025": {
        "name": "Rosar Vitclari",
        "stock": "23",
        "volume": "79213",
        "price": "55500"
    },
    "719038": {
        "name": "Nouver Vitclari",
        "stock": "5",
        "volume": "4128",
        "price": "167000000"
    },
    "719040": {
        "name": "Kutum Vitclari",
        "stock": "28",
        "volume": "14507",
        "price": "180000000"
    },
    "730704": {
        "name": "Pau Quoratum",
        "stock": "321",
        "volume": "18980",
        "price": "18000"
    },
    "730705": {
        "name": "Luka Quoratum",
        "stock": "5741",
        "volume": "53872",
        "price": "21100"
    },
    "730706": {
        "name": "Vishur Quoratum",
        "stock": "1083",
        "volume": "17633",
        "price": "24200"
    },
    "730710": {
        "name": "Krea Quoratum",
        "stock": "5293",
        "volume": "59055",
        "price": "27200"
    },
    "730711": {
        "name": "Rosar Quoratum",
        "stock": "3545",
        "volume": "77198",
        "price": "55500"
    },
    "730714": {
        "name": "Nouver Quoratum",
        "stock": "18",
        "volume": "5211",
        "price": "167000000"
    },
    "730716": {
        "name": "Kutum Quoratum",
        "stock": "36",
        "volume": "7332",
        "price": "180000000"
    }
}